{
    "id": 1129792,
    "joined_time": "2022-07-07T17:50:53.653838Z",
    "started_event": 1,
    "favourite_team": 4,
    "player_first_name": "Ivan",
    "player_last_name": "Krastilov",
    "player_region_id": 34,
    "player_region_name": "Bulgaria",
    "player_region_iso_code_short": "BG",
    "player_region_iso_code_long": "BGR",
    "summary_overall_points": 1414,
    "summary_overall_rank": 10270,
    "summary_event_points": 72,
    "summary_event_rank": 402794,
    "current_event": 22,
    "leagues": {
        "classic": [
            {
                "id": 4,
                "name": "Brentford",
                "short_name": "team-4",
                "created": "2022-07-05T09:51:58.235859Z",
                "closed": false,
                "rank": null,
                "max_entries": null,
                "league_type": "s",
                "scoring": "c",
                "admin_entry": null,
                "start_event": 1,
                "entry_can_leave": false,
                "entry_can_admin": false,
                "entry_can_invite": false,
                "has_cup": true,
                "cup_league": null,
                "cup_qualified": null,
                "entry_rank": 49,
                "entry_last_rank": 53
            },
            {
                "id": 54,
                "name": "Bulgaria",
                "short_name": "region-34",
                "created": "2022-07-05T09:51:58.638628Z",
                "closed": false,
                "rank": null,
                "max_entries": null,
                "league_type": "s",
                "scoring": "c",
                "admin_entry": null,
                "start_event": 1,
                "entry_can_leave": false,
                "entry_can_admin": false,
                "entry_can_invite": false,
                "has_cup": true,
                "cup_league": null,
                "cup_qualified": null,
                "entry_rank": 45,
                "entry_last_rank": 57
            },
            {
                "id": 276,
                "name": "Gameweek 1",
                "short_name": "event-1",
                "created": "2022-07-05T09:52:00.459050Z",
                "closed": false,
                "rank": null,
                "max_entries": null,
                "league_type": "s",
                "scoring": "c",
                "admin_entry": null,
                "start_event": 1,
                "entry_can_leave": false,
                "entry_can_admin": false,
                "entry_can_invite": false,
                "has_cup": false,
                "cup_league": null,
                "cup_qualified": null,
                "entry_rank": 10269,
                "entry_last_rank": 12415
            },
            {
                "id": 314,
                "name": "Overall",
                "short_name": "overall",
                "created": "2022-07-05T09:52:00.763442Z",
                "closed": false,
                "rank": null,
                "max_entries": null,
                "league_type": "s",
                "scoring": "c",
                "admin_entry": null,
                "start_event": 1,
                "entry_can_leave": false,
                "entry_can_admin": false,
                "entry_can_invite": false,
                "has_cup": true,
                "cup_league": 2371740,
                "cup_qualified": true,
                "entry_rank": 10270,
                "entry_last_rank": 12418
            },
            {
                "id": 916,
                "name": "042/ZARATA",
                "short_name": null,
                "created": "2022-07-05T15:12:09.786895Z",
                "closed": true,
                "rank": null,
                "max_entries": null,
                "league_type": "x",
                "scoring": "c",
                "admin_entry": 6554,
                "start_event": 1,
                "entry_can_leave": true,
                "entry_can_admin": false,
                "entry_can_invite": false,
                "has_cup": true,
                "cup_league": null,
                "cup_qualified": null,
                "entry_rank": 7,
                "entry_last_rank": 7
            },
            {
                "id": 102187,
                "name": "Sudden Death by FPLBG",
                "short_name": null,
                "created": "2022-07-06T06:34:05.287262Z",
                "closed": true,
                "rank": null,
                "max_entries": null,
                "league_type": "x",
                "scoring": "c",
                "admin_entry": 1370708,
                "start_event": 22,
                "entry_can_leave": true,
                "entry_can_admin": false,
                "entry_can_invite": false,
                "has_cup": true,
                "cup_league": null,
                "cup_qualified": null,
                "entry_rank": 57,
                "entry_last_rank": 86
            },
            {
                "id": 169926,
                "name": "fplbg",
                "short_name": null,
                "created": "2022-07-06T19:29:27.321449Z",
                "closed": false,
                "rank": null,
                "max_entries": null,
                "league_type": "x",
                "scoring": "c",
                "admin_entry": 880923,
                "start_event": 1,
                "entry_can_leave": true,
                "entry_can_admin": false,
                "entry_can_invite": false,
                "has_cup": true,
                "cup_league": null,
                "cup_qualified": null,
                "entry_rank": 15,
                "entry_last_rank": 14
            },
            {
                "id": 240787,
                "name": "ffstars.com",
                "short_name": null,
                "created": "2022-07-08T09:49:50.078958Z",
                "closed": false,
                "rank": null,
                "max_entries": null,
                "league_type": "x",
                "scoring": "c",
                "admin_entry": 1044362,
                "start_event": 1,
                "entry_can_leave": true,
                "entry_can_admin": false,
                "entry_can_invite": false,
                "has_cup": true,
                "cup_league": null,
                "cup_qualified": null,
                "entry_rank": 17,
                "entry_last_rank": 17
            },
            {
                "id": 481846,
                "name": "Bako Fantasy",
                "short_name": null,
                "created": "2022-07-16T20:14:40.489834Z",
                "closed": false,
                "rank": null,
                "max_entries": null,
                "league_type": "x",
                "scoring": "c",
                "admin_entry": 2410580,
                "start_event": 1,
                "entry_can_leave": true,
                "entry_can_admin": false,
                "entry_can_invite": false,
                "has_cup": true,
                "cup_league": null,
                "cup_qualified": null,
                "entry_rank": 1,
                "entry_last_rank": 1
            },
            {
                "id": 561321,
                "name": "градЪ 22/23",
                "short_name": null,
                "created": "2022-07-20T12:03:20.116079Z",
                "closed": false,
                "rank": null,
                "max_entries": null,
                "league_type": "x",
                "scoring": "c",
                "admin_entry": 35055,
                "start_event": 1,
                "entry_can_leave": true,
                "entry_can_admin": false,
                "entry_can_invite": false,
                "has_cup": true,
                "cup_league": null,
                "cup_qualified": null,
                "entry_rank": 1,
                "entry_last_rank": 1
            },
            {
                "id": 993738,
                "name": "Point Bet - Free Classic",
                "short_name": null,
                "created": "2022-07-31T10:10:55.655794Z",
                "closed": false,
                "rank": null,
                "max_entries": null,
                "league_type": "x",
                "scoring": "c",
                "admin_entry": 2021453,
                "start_event": 1,
                "entry_can_leave": true,
                "entry_can_admin": false,
                "entry_can_invite": false,
                "has_cup": true,
                "cup_league": null,
                "cup_qualified": null,
                "entry_rank": 1,
                "entry_last_rank": 1
            },
            {
                "id": 1225135,
                "name": "The A Team",
                "short_name": null,
                "created": "2022-08-03T07:16:53.071061Z",
                "closed": false,
                "rank": null,
                "max_entries": null,
                "league_type": "x",
                "scoring": "c",
                "admin_entry": 147462,
                "start_event": 1,
                "entry_can_leave": true,
                "entry_can_admin": false,
                "entry_can_invite": true,
                "has_cup": true,
                "cup_league": null,
                "cup_qualified": null,
                "entry_rank": 1,
                "entry_last_rank": 1
            },
            {
                "id": 2385997,
                "name": "Second Chance",
                "short_name": "sc",
                "created": "2022-12-13T09:32:14.682834Z",
                "closed": false,
                "rank": null,
                "max_entries": null,
                "league_type": "s",
                "scoring": "c",
                "admin_entry": null,
                "start_event": 17,
                "entry_can_leave": false,
                "entry_can_admin": false,
                "entry_can_invite": false,
                "has_cup": false,
                "cup_league": null,
                "cup_qualified": null,
                "entry_rank": 104732,
                "entry_last_rank": 142649
            },
            {
                "id": 2423694,
                "name": "Букмейкър Рейтинги",
                "short_name": null,
                "created": "2023-01-12T19:52:55.368658Z",
                "closed": false,
                "rank": null,
                "max_entries": null,
                "league_type": "x",
                "scoring": "c",
                "admin_entry": 95085,
                "start_event": 1,
                "entry_can_leave": true,
                "entry_can_admin": false,
                "entry_can_invite": false,
                "has_cup": true,
                "cup_league": null,
                "cup_qualified": null,
                "entry_rank": 3,
                "entry_last_rank": 3
            },
            {
                "id": 2423749,
                "name": "League 2423749",
                "short_name": null,
                "created": "2023-01-12T20:57:37.312321Z",
                "closed": true,
                "rank": null,
                "max_entries": null,
                "league_type": "c",
                "scoring": "c",
                "admin_entry": null,
                "start_event": 20,
                "entry_can_leave": true,
                "entry_can_admin": false,
                "entry_can_invite": false,
                "has_cup": false,
                "cup_league": null,
                "cup_qualified": null,
                "entry_rank": 1,
                "entry_last_rank": 1
            }
        ],
        "h2h": [
            {
                "id": 23221,
                "name": "League 2 Zara h2h B",
                "short_name": null,
                "created": "2022-07-05T17:05:13.944033Z",
                "closed": true,
                "rank": null,
                "max_entries": null,
                "league_type": "x",
                "scoring": "h",
                "admin_entry": 29690,
                "start_event": 1,
                "entry_can_leave": false,
                "entry_can_admin": false,
                "entry_can_invite": false,
                "has_cup": false,
                "cup_league": null,
                "cup_qualified": null,
                "entry_rank": 10,
                "entry_last_rank": 10
            },
            {
                "id": 844683,
                "name": "H2H Second Division",
                "short_name": null,
                "created": "2022-07-28T11:41:17.029538Z",
                "closed": true,
                "rank": null,
                "max_entries": null,
                "league_type": "x",
                "scoring": "h",
                "admin_entry": 1044362,
                "start_event": 1,
                "entry_can_leave": false,
                "entry_can_admin": false,
                "entry_can_invite": false,
                "has_cup": false,
                "cup_league": null,
                "cup_qualified": null,
                "entry_rank": 54,
                "entry_last_rank": 54
            }
        ],
        "cup": {
            "matches": [],
            "status": {
                "qualification_event": null,
                "qualification_numbers": null,
                "qualification_rank": null,
                "qualification_state": null
            },
            "cup_league": null
        },
        "cup_matches": [
            {
                "id": 76079666,
                "entry_1_entry": 1129792,
                "entry_1_name": "Bako Team",
                "entry_1_player_name": "Ivan Krastilov",
                "entry_1_points": 50,
                "entry_1_win": 0,
                "entry_1_draw": 0,
                "entry_1_loss": 0,
                "entry_1_total": 0,
                "entry_2_entry": 2864157,
                "entry_2_name": "Where Divocks Origi",
                "entry_2_player_name": "Fergal Keane",
                "entry_2_points": 55,
                "entry_2_win": 0,
                "entry_2_draw": 0,
                "entry_2_loss": 0,
                "entry_2_total": 0,
                "is_knockout": true,
                "league": 2371740,
                "winner": 2864157,
                "seed_value": null,
                "event": 18,
                "tiebreak": null,
                "is_bye": false,
                "knockout_name": "Round of 2097152"
            }
        ]
    },
    "name": "Bako Team",
    "name_change_blocked": false,
    "kit": "{\"kit_shirt_type\":\"stripes\",\"kit_shirt_base\":\"#000000\",\"kit_shirt_sleeves\":\"#ffffff\",\"kit_shirt_secondary\":\"#ffffff\",\"kit_shirt_logo\":\"no-racism\",\"kit_shorts\":\"#ffffff\",\"kit_socks_type\":\"plain\",\"kit_socks_base\":\"#ffffff\",\"kit_socks_secondary\":\"#E1E1E1\"}",
    "last_deadline_bank": 38,
    "last_deadline_value": 1042,
    "last_deadline_total_transfers": 28
}